timeseriesql_matplotlib/__init__.py
timeseriesql_matplotlib-0.0.2.dist-info/LICENSE
timeseriesql_matplotlib-0.0.2.dist-info/METADATA
timeseriesql_matplotlib-0.0.2.dist-info/WHEEL
timeseriesql_matplotlib-0.0.2.dist-info/top_level.txt
timeseriesql_matplotlib-0.0.2.dist-info/RECORD
