Metadata-Version: 2.1
Name: timeseriesql-matplotlib
Version: 0.0.2
Summary: A plotting backend for the TimeSeriesQL library
Home-page: http://github.com/mbeale/timeseriesql-matplotlib
Author: Michael Beale
Author-email: michael.beale@gmail.com
License: MIT
Platform: UNKNOWN
Classifier: Programming Language :: Python :: 3
Classifier: License :: OSI Approved :: MIT License
Classifier: Operating System :: OS Independent
Classifier: Development Status :: 3 - Alpha
Requires-Python: >=3.6
Requires-Dist: timeseriesql
Requires-Dist: matplotlib
